{
  "content": "Obrien Group.\nINVOICE\n8854 Aguilar Loaf | Russellville, IL 83762\nNo: 4578499101\nDate: 01/17/2025\nDue: 02/22/2026\nFROM\nBILL TO\n Obrien Group\n Maynard, Mullen and Oneal\n8854 Aguilar Loaf\n01262 Emily Harbors\nRussellville, IL 83762\nDavidton, CO 90702\nDescription\nQuantity\nUnit Price\nAmount\nReoonoad panqeua-qan nsnqel\n3.00\n257.16\n771.48\n2\nAutomated heuristio productivity\n5.00\n422.91\n2 114.55\n3\nExclusive uniform architecture\n9.00\n253.59\n2 282.31\nProgressive high-level cireuit\n10.00\n484.09\n4 840.90\nNetworked 24/7 orchestratior\n5.00\n491.09\n2 455.45\nSubtotal\n12 464.69\nTax (10%)\n1 246.47\nDiscoun!\n-1 246.47\nTotal Due\n12 484.69\nPAYMENT INFORMATION\nBank: Sanchez. Abbotl and White Bank\nAccount: RDRI82356408830004\nank you ioryou",
  "detections": [
    {
      "text": "Obrien Group.",
      "confidence": 0.9744447469711304,
      "bbox": [
        [
          19.0,
          20.0
        ],
        [
          163.0,
          24.0
        ],
        [
          163.0,
          45.0
        ],
        [
          19.0,
          41.0
        ]
      ]
    },
    {
      "text": "INVOICE",
      "confidence": 0.99810391664505,
      "bbox": [
        [
          658.0,
          22.0
        ],
        [
          776.0,
          22.0
        ],
        [
          776.0,
          47.0
        ],
        [
          658.0,
          47.0
        ]
      ]
    },
    {
      "text": "8854 Aguilar Loaf | Russellville, IL 83762",
      "confidence": 0.9844853281974792,
      "bbox": [
        [
          18.0,
          49.0
        ],
        [
          202.0,
          49.0
        ],
        [
          202.0,
          64.0
        ],
        [
          18.0,
          64.0
        ]
      ]
    },
    {
      "text": "No: 4578499101",
      "confidence": 0.9984737038612366,
      "bbox": [
        [
          690.0,
          56.0
        ],
        [
          774.0,
          56.0
        ],
        [
          774.0,
          69.0
        ],
        [
          690.0,
          69.0
        ]
      ]
    },
    {
      "text": "Date: 01/17/2025",
      "confidence": 0.9997803568840027,
      "bbox": [
        [
          688.0,
          74.0
        ],
        [
          775.0,
          74.0
        ],
        [
          775.0,
          87.0
        ],
        [
          688.0,
          87.0
        ]
      ]
    },
    {
      "text": "Due: 02/22/2026",
      "confidence": 0.9995280504226685,
      "bbox": [
        [
          691.0,
          91.0
        ],
        [
          775.0,
          91.0
        ],
        [
          775.0,
          104.0
        ],
        [
          691.0,
          104.0
        ]
      ]
    },
    {
      "text": "FROM",
      "confidence": 0.999252200126648,
      "bbox": [
        [
          18.0,
          150.0
        ],
        [
          54.0,
          150.0
        ],
        [
          54.0,
          163.0
        ],
        [
          18.0,
          163.0
        ]
      ]
    },
    {
      "text": "BILL TO",
      "confidence": 0.9968600273132324,
      "bbox": [
        [
          434.0,
          150.0
        ],
        [
          479.0,
          150.0
        ],
        [
          479.0,
          163.0
        ],
        [
          434.0,
          163.0
        ]
      ]
    },
    {
      "text": " Obrien Group",
      "confidence": 0.9699302911758423,
      "bbox": [
        [
          17.0,
          167.0
        ],
        [
          101.0,
          170.0
        ],
        [
          100.0,
          185.0
        ],
        [
          16.0,
          182.0
        ]
      ]
    },
    {
      "text": " Maynard, Mullen and Oneal",
      "confidence": 0.9912322759628296,
      "bbox": [
        [
          431.0,
          167.0
        ],
        [
          592.0,
          168.0
        ],
        [
          592.0,
          185.0
        ],
        [
          431.0,
          184.0
        ]
      ]
    },
    {
      "text": "8854 Aguilar Loaf",
      "confidence": 0.9638285040855408,
      "bbox": [
        [
          18.0,
          185.0
        ],
        [
          99.0,
          186.0
        ],
        [
          99.0,
          199.0
        ],
        [
          18.0,
          198.0
        ]
      ]
    },
    {
      "text": "01262 Emily Harbors",
      "confidence": 0.9785929322242737,
      "bbox": [
        [
          434.0,
          185.0
        ],
        [
          529.0,
          185.0
        ],
        [
          529.0,
          200.0
        ],
        [
          434.0,
          200.0
        ]
      ]
    },
    {
      "text": "Russellville, IL 83762",
      "confidence": 0.9594702124595642,
      "bbox": [
        [
          19.0,
          198.0
        ],
        [
          115.0,
          198.0
        ],
        [
          115.0,
          209.0
        ],
        [
          19.0,
          209.0
        ]
      ]
    },
    {
      "text": "Davidton, CO 90702",
      "confidence": 0.9705966114997864,
      "bbox": [
        [
          434.0,
          198.0
        ],
        [
          527.0,
          198.0
        ],
        [
          527.0,
          209.0
        ],
        [
          434.0,
          209.0
        ]
      ]
    },
    {
      "text": "Description",
      "confidence": 0.9996138215065002,
      "bbox": [
        [
          64.0,
          247.0
        ],
        [
          123.0,
          247.0
        ],
        [
          123.0,
          260.0
        ],
        [
          64.0,
          260.0
        ]
      ]
    },
    {
      "text": "Quantity",
      "confidence": 0.9576574563980103,
      "bbox": [
        [
          496.0,
          243.0
        ],
        [
          542.0,
          246.0
        ],
        [
          540.0,
          262.0
        ],
        [
          495.0,
          259.0
        ]
      ]
    },
    {
      "text": "Unit Price",
      "confidence": 0.9995183944702148,
      "bbox": [
        [
          603.0,
          242.0
        ],
        [
          656.0,
          245.0
        ],
        [
          655.0,
          261.0
        ],
        [
          602.0,
          258.0
        ]
      ]
    },
    {
      "text": "Amount",
      "confidence": 0.9995235800743103,
      "bbox": [
        [
          726.0,
          244.0
        ],
        [
          769.0,
          247.0
        ],
        [
          769.0,
          260.0
        ],
        [
          725.0,
          257.0
        ]
      ]
    },
    {
      "text": "Reoonoad panqeua-qan nsnqel",
      "confidence": 0.5456358194351196,
      "bbox": [
        [
          65.0,
          280.0
        ],
        [
          196.0,
          280.0
        ],
        [
          196.0,
          291.0
        ],
        [
          65.0,
          291.0
        ]
      ]
    },
    {
      "text": "3.00",
      "confidence": 0.9997641444206238,
      "bbox": [
        [
          518.0,
          278.0
        ],
        [
          542.0,
          278.0
        ],
        [
          542.0,
          292.0
        ],
        [
          518.0,
          292.0
        ]
      ]
    },
    {
      "text": "257.16",
      "confidence": 0.9987542629241943,
      "bbox": [
        [
          619.0,
          277.0
        ],
        [
          657.0,
          277.0
        ],
        [
          657.0,
          294.0
        ],
        [
          619.0,
          294.0
        ]
      ]
    },
    {
      "text": "771.48",
      "confidence": 0.9835410118103027,
      "bbox": [
        [
          732.0,
          277.0
        ],
        [
          768.0,
          280.0
        ],
        [
          767.0,
          295.0
        ],
        [
          731.0,
          292.0
        ]
      ]
    },
    {
      "text": "2",
      "confidence": 0.9997269511222839,
      "bbox": [
        [
          27.0,
          314.0
        ],
        [
          34.0,
          314.0
        ],
        [
          34.0,
          324.0
        ],
        [
          27.0,
          324.0
        ]
      ]
    },
    {
      "text": "Automated heuristio productivity",
      "confidence": 0.99094158411026,
      "bbox": [
        [
          64.0,
          310.0
        ],
        [
          208.0,
          311.0
        ],
        [
          208.0,
          326.0
        ],
        [
          64.0,
          325.0
        ]
      ]
    },
    {
      "text": "5.00",
      "confidence": 0.9997426271438599,
      "bbox": [
        [
          518.0,
          311.0
        ],
        [
          542.0,
          311.0
        ],
        [
          542.0,
          325.0
        ],
        [
          518.0,
          325.0
        ]
      ]
    },
    {
      "text": "422.91",
      "confidence": 0.9241538047790527,
      "bbox": [
        [
          621.0,
          311.0
        ],
        [
          655.0,
          311.0
        ],
        [
          655.0,
          326.0
        ],
        [
          621.0,
          326.0
        ]
      ]
    },
    {
      "text": "2 114.55",
      "confidence": 0.9984467625617981,
      "bbox": [
        [
          725.0,
          311.0
        ],
        [
          768.0,
          311.0
        ],
        [
          768.0,
          324.0
        ],
        [
          725.0,
          324.0
        ]
      ]
    },
    {
      "text": "3",
      "confidence": 0.6811133027076721,
      "bbox": [
        [
          27.0,
          345.0
        ],
        [
          34.0,
          345.0
        ],
        [
          34.0,
          356.0
        ],
        [
          27.0,
          356.0
        ]
      ]
    },
    {
      "text": "Exclusive uniform architecture",
      "confidence": 0.9981159567832947,
      "bbox": [
        [
          65.0,
          344.0
        ],
        [
          200.0,
          344.0
        ],
        [
          200.0,
          356.0
        ],
        [
          65.0,
          356.0
        ]
      ]
    },
    {
      "text": "9.00",
      "confidence": 0.9991623163223267,
      "bbox": [
        [
          519.0,
          343.0
        ],
        [
          542.0,
          343.0
        ],
        [
          542.0,
          357.0
        ],
        [
          519.0,
          357.0
        ]
      ]
    },
    {
      "text": "253.59",
      "confidence": 0.9810280203819275,
      "bbox": [
        [
          620.0,
          340.0
        ],
        [
          655.0,
          343.0
        ],
        [
          654.0,
          357.0
        ],
        [
          619.0,
          354.0
        ]
      ]
    },
    {
      "text": "2 282.31",
      "confidence": 0.9975160360336304,
      "bbox": [
        [
          725.0,
          340.0
        ],
        [
          767.0,
          343.0
        ],
        [
          766.0,
          359.0
        ],
        [
          724.0,
          357.0
        ]
      ]
    },
    {
      "text": "Progressive high-level cireuit",
      "confidence": 0.9651004076004028,
      "bbox": [
        [
          64.0,
          373.0
        ],
        [
          194.0,
          376.0
        ],
        [
          194.0,
          391.0
        ],
        [
          64.0,
          388.0
        ]
      ]
    },
    {
      "text": "10.00",
      "confidence": 0.999559760093689,
      "bbox": [
        [
          514.0,
          374.0
        ],
        [
          542.0,
          374.0
        ],
        [
          542.0,
          388.0
        ],
        [
          514.0,
          388.0
        ]
      ]
    },
    {
      "text": "484.09",
      "confidence": 0.9981152415275574,
      "bbox": [
        [
          619.0,
          373.0
        ],
        [
          656.0,
          373.0
        ],
        [
          656.0,
          390.0
        ],
        [
          619.0,
          390.0
        ]
      ]
    },
    {
      "text": "4 840.90",
      "confidence": 0.9990828037261963,
      "bbox": [
        [
          725.0,
          376.0
        ],
        [
          768.0,
          376.0
        ],
        [
          768.0,
          388.0
        ],
        [
          725.0,
          388.0
        ]
      ]
    },
    {
      "text": "Networked 24/7 orchestratior",
      "confidence": 0.9922523498535156,
      "bbox": [
        [
          65.0,
          407.0
        ],
        [
          195.0,
          407.0
        ],
        [
          195.0,
          419.0
        ],
        [
          65.0,
          419.0
        ]
      ]
    },
    {
      "text": "5.00",
      "confidence": 0.9997426271438599,
      "bbox": [
        [
          518.0,
          407.0
        ],
        [
          542.0,
          407.0
        ],
        [
          542.0,
          421.0
        ],
        [
          518.0,
          421.0
        ]
      ]
    },
    {
      "text": "491.09",
      "confidence": 0.9986438155174255,
      "bbox": [
        [
          619.0,
          406.0
        ],
        [
          656.0,
          406.0
        ],
        [
          656.0,
          422.0
        ],
        [
          619.0,
          422.0
        ]
      ]
    },
    {
      "text": "2 455.45",
      "confidence": 0.9997100234031677,
      "bbox": [
        [
          725.0,
          407.0
        ],
        [
          768.0,
          407.0
        ],
        [
          768.0,
          420.0
        ],
        [
          725.0,
          420.0
        ]
      ]
    },
    {
      "text": "Subtotal",
      "confidence": 0.9979636669158936,
      "bbox": [
        [
          604.0,
          455.0
        ],
        [
          643.0,
          455.0
        ],
        [
          643.0,
          468.0
        ],
        [
          604.0,
          468.0
        ]
      ]
    },
    {
      "text": "12 464.69",
      "confidence": 0.975426435470581,
      "bbox": [
        [
          721.0,
          455.0
        ],
        [
          768.0,
          455.0
        ],
        [
          768.0,
          468.0
        ],
        [
          721.0,
          468.0
        ]
      ]
    },
    {
      "text": "Tax (10%)",
      "confidence": 0.998615562915802,
      "bbox": [
        [
          594.0,
          480.0
        ],
        [
          643.0,
          480.0
        ],
        [
          643.0,
          492.0
        ],
        [
          594.0,
          492.0
        ]
      ]
    },
    {
      "text": "1 246.47",
      "confidence": 0.9973889589309692,
      "bbox": [
        [
          727.0,
          480.0
        ],
        [
          768.0,
          480.0
        ],
        [
          768.0,
          492.0
        ],
        [
          727.0,
          492.0
        ]
      ]
    },
    {
      "text": "Discoun!",
      "confidence": 0.908308744430542,
      "bbox": [
        [
          599.0,
          500.0
        ],
        [
          647.0,
          503.0
        ],
        [
          646.0,
          520.0
        ],
        [
          598.0,
          517.0
        ]
      ]
    },
    {
      "text": "-1 246.47",
      "confidence": 0.940674364566803,
      "bbox": [
        [
          721.0,
          499.0
        ],
        [
          770.0,
          502.0
        ],
        [
          769.0,
          519.0
        ],
        [
          720.0,
          516.0
        ]
      ]
    },
    {
      "text": "Total Due",
      "confidence": 0.9973028898239136,
      "bbox": [
        [
          598.0,
          532.0
        ],
        [
          643.0,
          532.0
        ],
        [
          643.0,
          545.0
        ],
        [
          598.0,
          545.0
        ]
      ]
    },
    {
      "text": "12 484.69",
      "confidence": 0.9769593477249146,
      "bbox": [
        [
          722.0,
          532.0
        ],
        [
          768.0,
          532.0
        ],
        [
          768.0,
          545.0
        ],
        [
          722.0,
          545.0
        ]
      ]
    },
    {
      "text": "PAYMENT INFORMATION",
      "confidence": 0.9990727305412292,
      "bbox": [
        [
          32.0,
          591.0
        ],
        [
          152.0,
          591.0
        ],
        [
          152.0,
          602.0
        ],
        [
          32.0,
          602.0
        ]
      ]
    },
    {
      "text": "Bank: Sanchez. Abbotl and White Bank",
      "confidence": 0.9762253165245056,
      "bbox": [
        [
          31.0,
          608.0
        ],
        [
          210.0,
          608.0
        ],
        [
          210.0,
          623.0
        ],
        [
          31.0,
          623.0
        ]
      ]
    },
    {
      "text": "Account: RDRI82356408830004",
      "confidence": 0.980919361114502,
      "bbox": [
        [
          32.0,
          623.0
        ],
        [
          182.0,
          623.0
        ],
        [
          182.0,
          635.0
        ],
        [
          32.0,
          635.0
        ]
      ]
    },
    {
      "text": "ank you ioryou",
      "confidence": 0.781613290309906,
      "bbox": [
        [
          349.0,
          681.0
        ],
        [
          412.0,
          681.0
        ],
        [
          412.0,
          689.0
        ],
        [
          349.0,
          689.0
        ]
      ]
    }
  ]
}