{
  "model_id": "prebuilt-invoice",
  "api_version": "2023-07-31",
  "content": "Andersen-Ward\nINVOICE\n61434 Humphrey Lodge | Tracyport, NV 74313\nNo: 2508674769\nDate: 12/04/2025\nDue: 03/09/2026\nFROM\nBILL TO\nAndersen-Ward\nBriggs LLC\n61434 Humphrey Lodge\n0677 James Gardens Suite 403\nTracyport, NV 74313\nLake Sharon, OK 48077\n#\nDescription\nQuantity\nUnit Price\nAmount\n1\nBalanced next generation product\n2.00\n333.76\n687.52\n2\nProgrammable bifurcated benchmark\n9.00\n152.43\n1 371.87\n3\nImplemented 6thgeneration groupware\n4.00\n140.87\n563.48\nOID\nSubtotal\n2 602.87\nTax (10%)\n260.29\nD. Taylor 07/01/25\nDiscount\n-260.29\nTotal Due\n2 602.87\nPAYMENT INFORMATION\nBank: Wiley-Prince Credit Union\nAccount: RLQB28889921597010\nMethod: Check\nThank you for your business",
  "pages": [
    {
      "page_number": 1,
      "width": 8.2639,
      "height": 11.6944,
      "unit": "inch",
      "angle": null,
      "words": [
        {
          "content": "Andersen-Ward",
          "confidence": 0.991,
          "polygon": [
            {
              "x": 0.2081,
              "y": 0.2233
            },
            {
              "x": 1.8731,
              "y": 0.2183
            },
            {
              "x": 1.8782,
              "y": 0.4467
            },
            {
              "x": 0.2081,
              "y": 0.4517
            }
          ]
        },
        {
          "content": "INVOICE",
          "confidence": 0.993,
          "polygon": [
            {
              "x": 6.8629,
              "y": 0.2386
            },
            {
              "x": 7.9949,
              "y": 0.2335
            },
            {
              "x": 7.9999,
              "y": 0.4873
            },
            {
              "x": 6.8578,
              "y": 0.4923
            }
          ]
        },
        {
          "content": "61434",
          "confidence": 0.993,
          "polygon": [
            {
              "x": 0.198,
              "y": 0.5177
            },
            {
              "x": 0.4822,
              "y": 0.5177
            },
            {
              "x": 0.4772,
              "y": 0.6548
            },
            {
              "x": 0.198,
              "y": 0.6548
            }
          ]
        },
        {
          "content": "Humphrey",
          "confidence": 0.992,
          "polygon": [
            {
              "x": 0.5076,
              "y": 0.5177
            },
            {
              "x": 0.9949,
              "y": 0.5177
            },
            {
              "x": 0.9898,
              "y": 0.6598
            },
            {
              "x": 0.5076,
              "y": 0.6548
            }
          ]
        },
        {
          "content": "Lodge",
          "confidence": 0.995,
          "polygon": [
            {
              "x": 1.0203,
              "y": 0.5177
            },
            {
              "x": 1.3046,
              "y": 0.5177
            },
            {
              "x": 1.3046,
              "y": 0.6598
            },
            {
              "x": 1.0203,
              "y": 0.6598
            }
          ]
        },
        {
          "content": "|",
          "confidence": 0.919,
          "polygon": [
            {
              "x": 1.3299,
              "y": 0.5177
            },
            {
              "x": 1.3858,
              "y": 0.5177
            },
            {
              "x": 1.3858,
              "y": 0.6598
            },
            {
              "x": 1.3299,
              "y": 0.6598
            }
          ]
        },
        {
          "content": "Tracyport,",
          "confidence": 0.961,
          "polygon": [
            {
              "x": 1.4112,
              "y": 0.5177
            },
            {
              "x": 1.8629,
              "y": 0.5177
            },
            {
              "x": 1.8579,
              "y": 0.6598
            },
            {
              "x": 1.4112,
              "y": 0.6598
            }
          ]
        },
        {
          "content": "NV",
          "confidence": 0.985,
          "polygon": [
            {
              "x": 1.8883,
              "y": 0.5177
            },
            {
              "x": 2.0457,
              "y": 0.5177
            },
            {
              "x": 2.0406,
              "y": 0.6598
            },
            {
              "x": 1.8883,
              "y": 0.6598
            }
          ]
        },
        {
          "content": "74313",
          "confidence": 0.988,
          "polygon": [
            {
              "x": 2.071,
              "y": 0.5177
            },
            {
              "x": 2.3705,
              "y": 0.5177
            },
            {
              "x": 2.3655,
              "y": 0.6548
            },
            {
              "x": 2.071,
              "y": 0.6598
            }
          ]
        },
        {
          "content": "No:",
          "confidence": 0.951,
          "polygon": [
            {
              "x": 7.1928,
              "y": 0.5888
            },
            {
              "x": 7.3908,
              "y": 0.5888
            },
            {
              "x": 7.3908,
              "y": 0.7157
            },
            {
              "x": 7.1928,
              "y": 0.7106
            }
          ]
        },
        {
          "content": "2508674769",
          "confidence": 0.983,
          "polygon": [
            {
              "x": 7.4162,
              "y": 0.5888
            },
            {
              "x": 8.0608,
              "y": 0.5939
            },
            {
              "x": 8.0558,
              "y": 0.7157
            },
            {
              "x": 7.4162,
              "y": 0.7157
            }
          ]
        },
        {
          "content": "Date:",
          "confidence": 0.993,
          "polygon": [
            {
              "x": 7.1573,
              "y": 0.7766
            },
            {
              "x": 7.4619,
              "y": 0.7715
            },
            {
              "x": 7.4619,
              "y": 0.8933
            },
            {
              "x": 7.1573,
              "y": 0.8933
            }
          ]
        },
        {
          "content": "12/04/2025",
          "confidence": 0.988,
          "polygon": [
            {
              "x": 7.4923,
              "y": 0.7715
            },
            {
              "x": 8.0558,
              "y": 0.7715
            },
            {
              "x": 8.0507,
              "y": 0.8933
            },
            {
              "x": 7.4923,
              "y": 0.8933
            }
          ]
        },
        {
          "content": "Due:",
          "confidence": 0.989,
          "polygon": [
            {
              "x": 7.1928,
              "y": 0.9441
            },
            {
              "x": 7.4517,
              "y": 0.9441
            },
            {
              "x": 7.4568,
              "y": 1.071
            },
            {
              "x": 7.1979,
              "y": 1.0761
            }
          ]
        },
        {
          "content": "03/09/2026",
          "confidence": 0.989,
          "polygon": [
            {
              "x": 7.4771,
              "y": 0.9441
            },
            {
              "x": 8.0507,
              "y": 0.9492
            },
            {
              "x": 8.0507,
              "y": 1.0659
            },
            {
              "x": 7.4822,
              "y": 1.071
            }
          ]
        },
        {
          "content": "FROM",
          "confidence": 0.993,
          "polygon": [
            {
              "x": 0.203,
              "y": 1.5633
            },
            {
              "x": 0.5076,
              "y": 1.5633
            },
            {
              "x": 0.5076,
              "y": 1.6902
            },
            {
              "x": 0.203,
              "y": 1.6851
            }
          ]
        },
        {
          "content": "BILL",
          "confidence": 0.991,
          "polygon": [
            {
              "x": 4.5127,
              "y": 1.5532
            },
            {
              "x": 4.7665,
              "y": 1.5582
            },
            {
              "x": 4.7665,
              "y": 1.6902
            },
            {
              "x": 4.5177,
              "y": 1.6851
            }
          ]
        },
        {
          "content": "TO",
          "confidence": 0.996,
          "polygon": [
            {
              "x": 4.8071,
              "y": 1.5582
            },
            {
              "x": 4.9492,
              "y": 1.5582
            },
            {
              "x": 4.9492,
              "y": 1.6902
            },
            {
              "x": 4.8121,
              "y": 1.6902
            }
          ]
        },
        {
          "content": "Andersen-Ward",
          "confidence": 0.992,
          "polygon": [
            {
              "x": 0.203,
              "y": 1.7714
            },
            {
              "x": 1.1269,
              "y": 1.7663
            },
            {
              "x": 1.1269,
              "y": 1.9085
            },
            {
              "x": 0.2081,
              "y": 1.9135
            }
          ]
        },
        {
          "content": "Briggs",
          "confidence": 0.994,
          "polygon": [
            {
              "x": 4.5177,
              "y": 1.7663
            },
            {
              "x": 4.9137,
              "y": 1.7663
            },
            {
              "x": 4.9137,
              "y": 1.9135
            },
            {
              "x": 4.5177,
              "y": 1.9135
            }
          ]
        },
        {
          "content": "LLC",
          "confidence": 0.994,
          "polygon": [
            {
              "x": 4.9441,
              "y": 1.7663
            },
            {
              "x": 5.1827,
              "y": 1.7613
            },
            {
              "x": 5.1878,
              "y": 1.9186
            },
            {
              "x": 4.9441,
              "y": 1.9135
            }
          ]
        },
        {
          "content": "61434",
          "confidence": 0.994,
          "polygon": [
            {
              "x": 0.1929,
              "y": 1.944
            },
            {
              "x": 0.4873,
              "y": 1.944
            },
            {
              "x": 0.4873,
              "y": 2.0658
            },
            {
              "x": 0.198,
              "y": 2.0607
            }
          ]
        },
        {
          "content": "Humphrey",
          "confidence": 0.993,
          "polygon": [
            {
              "x": 0.5127,
              "y": 1.944
            },
            {
              "x": 0.9949,
              "y": 1.9491
            },
            {
              "x": 0.9949,
              "y": 2.0709
            },
            {
              "x": 0.5127,
              "y": 2.0658
            }
          ]
        },
        {
          "content": "Lodge",
          "confidence": 0.993,
          "polygon": [
            {
              "x": 1.0203,
              "y": 1.9491
            },
            {
              "x": 1.3249,
              "y": 1.944
            },
            {
              "x": 1.3249,
              "y": 2.076
            },
            {
              "x": 1.0203,
              "y": 2.0709
            }
          ]
        },
        {
          "content": "0677",
          "confidence": 0.775,
          "polygon": [
            {
              "x": 4.5177,
              "y": 1.9389
            },
            {
              "x": 4.7563,
              "y": 1.9389
            },
            {
              "x": 4.7563,
              "y": 2.0607
            },
            {
              "x": 4.5177,
              "y": 2.0658
            }
          ]
        },
        {
          "content": "James",
          "confidence": 0.993,
          "polygon": [
            {
              "x": 4.7817,
              "y": 1.9389
            },
            {
              "x": 5.0913,
              "y": 1.944
            },
            {
              "x": 5.0913,
              "y": 2.0607
            },
            {
              "x": 4.7817,
              "y": 2.0607
            }
          ]
        },
        {
          "content": "Gardens",
          "confidence": 0.991,
          "polygon": [
            {
              "x": 5.1167,
              "y": 1.944
            },
            {
              "x": 5.5228,
              "y": 1.944
            },
            {
              "x": 5.5228,
              "y": 2.0607
            },
            {
              "x": 5.1167,
              "y": 2.0607
            }
          ]
        },
        {
          "content": "Suite",
          "confidence": 0.995,
          "polygon": [
            {
              "x": 5.5482,
              "y": 1.944
            },
            {
              "x": 5.7868,
              "y": 1.9389
            },
            {
              "x": 5.7868,
              "y": 2.0607
            },
            {
              "x": 5.5482,
              "y": 2.0607
            }
          ]
        },
        {
          "content": "403",
          "confidence": 0.995,
          "polygon": [
            {
              "x": 5.8121,
              "y": 1.9389
            },
            {
              "x": 5.9949,
              "y": 1.9389
            },
            {
              "x": 5.9949,
              "y": 2.0658
            },
            {
              "x": 5.8121,
              "y": 2.0607
            }
          ]
        },
        {
          "content": "Tracyport,",
          "confidence": 0.989,
          "polygon": [
            {
              "x": 0.203,
              "y": 2.0607
            },
            {
              "x": 0.67,
              "y": 2.0607
            },
            {
              "x": 0.665,
              "y": 2.1826
            },
            {
              "x": 0.203,
              "y": 2.1775
            }
          ]
        },
        {
          "content": "NV",
          "confidence": 0.962,
          "polygon": [
            {
              "x": 0.6903,
              "y": 2.0607
            },
            {
              "x": 0.8376,
              "y": 2.0607
            },
            {
              "x": 0.8376,
              "y": 2.1775
            },
            {
              "x": 0.6903,
              "y": 2.1826
            }
          ]
        },
        {
          "content": "74313",
          "confidence": 0.987,
          "polygon": [
            {
              "x": 0.8782,
              "y": 2.0607
            },
            {
              "x": 1.1675,
              "y": 2.0607
            },
            {
              "x": 1.1675,
              "y": 2.1775
            },
            {
              "x": 0.8731,
              "y": 2.1775
            }
          ]
        },
        {
          "content": "Lake",
          "confidence": 0.993,
          "polygon": [
            {
              "x": 4.5127,
              "y": 2.0607
            },
            {
              "x": 4.7411,
              "y": 2.0607
            },
            {
              "x": 4.7411,
              "y": 2.1775
            },
            {
              "x": 4.5177,
              "y": 2.1775
            }
          ]
        },
        {
          "content": "Sharon,",
          "confidence": 0.974,
          "polygon": [
            {
              "x": 4.7766,
              "y": 2.0607
            },
            {
              "x": 5.1472,
              "y": 2.0607
            },
            {
              "x": 5.1472,
              "y": 2.1724
            },
            {
              "x": 4.7817,
              "y": 2.1775
            }
          ]
        },
        {
          "content": "OK",
          "confidence": 0.993,
          "polygon": [
            {
              "x": 5.1675,
              "y": 2.0607
            },
            {
              "x": 5.3096,
              "y": 2.0607
            },
            {
              "x": 5.3147,
              "y": 2.1724
            },
            {
              "x": 5.1725,
              "y": 2.1724
            }
          ]
        },
        {
          "content": "48077",
          "confidence": 0.993,
          "polygon": [
            {
              "x": 5.3502,
              "y": 2.0607
            },
            {
              "x": 5.6446,
              "y": 2.0607
            },
            {
              "x": 5.6497,
              "y": 2.1724
            },
            {
              "x": 5.3553,
              "y": 2.1724
            }
          ]
        },
        {
          "content": "#",
          "confidence": 0.993,
          "polygon": [
            {
              "x": 0.2741,
              "y": 2.5785
            },
            {
              "x": 0.3503,
              "y": 2.5785
            },
            {
              "x": 0.3553,
              "y": 2.6698
            },
            {
              "x": 0.2792,
              "y": 2.6698
            }
          ]
        },
        {
          "content": "Description",
          "confidence": 0.979,
          "polygon": [
            {
              "x": 0.6802,
              "y": 2.5785
            },
            {
              "x": 1.2436,
              "y": 2.5734
            },
            {
              "x": 1.2436,
              "y": 2.7003
            },
            {
              "x": 0.6802,
              "y": 2.6851
            }
          ]
        },
        {
          "content": "Quantity",
          "confidence": 0.994,
          "polygon": [
            {
              "x": 5.1928,
              "y": 2.5734
            },
            {
              "x": 5.6192,
              "y": 2.5734
            },
            {
              "x": 5.6142,
              "y": 2.6952
            },
            {
              "x": 5.1928,
              "y": 2.6901
            }
          ]
        },
        {
          "content": "Unit",
          "confidence": 0.961,
          "polygon": [
            {
              "x": 6.3045,
              "y": 2.5734
            },
            {
              "x": 6.5177,
              "y": 2.5734
            },
            {
              "x": 6.5177,
              "y": 2.68
            },
            {
              "x": 6.2994,
              "y": 2.6749
            }
          ]
        },
        {
          "content": "Price",
          "confidence": 0.995,
          "polygon": [
            {
              "x": 6.538,
              "y": 2.5734
            },
            {
              "x": 6.7867,
              "y": 2.5785
            },
            {
              "x": 6.7867,
              "y": 2.6851
            },
            {
              "x": 6.538,
              "y": 2.68
            }
          ]
        },
        {
          "content": "Amount",
          "confidence": 0.961,
          "polygon": [
            {
              "x": 7.5735,
              "y": 2.5835
            },
            {
              "x": 7.9847,
              "y": 2.5785
            },
            {
              "x": 7.9847,
              "y": 2.68
            },
            {
              "x": 7.5735,
              "y": 2.68
            }
          ]
        },
        {
          "content": "1",
          "confidence": 0.995,
          "polygon": [
            {
              "x": 0.3046,
              "y": 2.9236
            },
            {
              "x": 0.3452,
              "y": 2.9236
            },
            {
              "x": 0.3503,
              "y": 3.0099
            },
            {
              "x": 0.3096,
              "y": 3.015
            }
          ]
        },
        {
          "content": "Balanced",
          "confidence": 0.931,
          "polygon": [
            {
              "x": 0.67,
              "y": 2.9185
            },
            {
              "x": 1.1117,
              "y": 2.9135
            },
            {
              "x": 1.1117,
              "y": 3.0302
            },
            {
              "x": 0.6751,
              "y": 3.0251
            }
          ]
        },
        {
          "content": "next",
          "confidence": 0.993,
          "polygon": [
            {
              "x": 1.132,
              "y": 2.9135
            },
            {
              "x": 1.3401,
              "y": 2.9135
            },
            {
              "x": 1.3452,
              "y": 3.0353
            },
            {
              "x": 1.137,
              "y": 3.0302
            }
          ]
        },
        {
          "content": "generation",
          "confidence": 0.978,
          "polygon": [
            {
              "x": 1.3655,
              "y": 2.9135
            },
            {
              "x": 1.8579,
              "y": 2.9185
            },
            {
              "x": 1.8579,
              "y": 3.0404
            },
            {
              "x": 1.3655,
              "y": 3.0353
            }
          ]
        },
        {
          "content": "product",
          "confidence": 0.993,
          "polygon": [
            {
              "x": 1.8883,
              "y": 2.9185
            },
            {
              "x": 2.2487,
              "y": 2.9236
            },
            {
              "x": 2.2487,
              "y": 3.0404
            },
            {
              "x": 1.8883,
              "y": 3.0404
            }
          ]
        },
        {
          "content": "2.00",
          "confidence": 0.992,
          "polygon": [
            {
              "x": 5.4162,
              "y": 2.9135
            },
            {
              "x": 5.6142,
              "y": 2.9135
            },
            {
              "x": 5.6142,
              "y": 3.02
            },
            {
              "x": 5.4162,
              "y": 3.02
            }
          ]
        },
        {
          "content": "333.76",
          "confidence": 0.989,
          "polygon": [
            {
              "x": 6.472,
              "y": 2.9185
            },
            {
              "x": 6.7867,
              "y": 2.9185
            },
            {
              "x": 6.7867,
              "y": 3.0251
            },
            {
              "x": 6.472,
              "y": 3.02
            }
          ]
        },
        {
          "content": "687.52",
          "confidence": 0.759,
          "polygon": [
            {
              "x": 7.6497,
              "y": 2.9236
            },
            {
              "x": 7.9746,
              "y": 2.9185
            },
            {
              "x": 7.9746,
              "y": 3.02
            },
            {
              "x": 7.6497,
              "y": 3.02
            }
          ]
        },
        {
          "content": "2",
          "confidence": 0.993,
          "polygon": [
            {
              "x": 0.2893,
              "y": 3.2535
            },
            {
              "x": 0.3503,
              "y": 3.2535
            },
            {
              "x": 0.3503,
              "y": 3.3601
            },
            {
              "x": 0.2893,
              "y": 3.3601
            }
          ]
        },
        {
          "content": "Programmable",
          "confidence": 0.92,
          "polygon": [
            {
              "x": 0.6751,
              "y": 3.2637
            },
            {
              "x": 1.3553,
              "y": 3.2535
            },
            {
              "x": 1.3553,
              "y": 3.3601
            },
            {
              "x": 0.67,
              "y": 3.3703
            }
          ]
        },
        {
          "content": "bifurcated",
          "confidence": 0.592,
          "polygon": [
            {
              "x": 1.3858,
              "y": 3.2535
            },
            {
              "x": 1.8477,
              "y": 3.2485
            },
            {
              "x": 1.8477,
              "y": 3.3601
            },
            {
              "x": 1.3858,
              "y": 3.3601
            }
          ]
        },
        {
          "content": "benchmark",
          "confidence": 0.968,
          "polygon": [
            {
              "x": 1.8731,
              "y": 3.2485
            },
            {
              "x": 2.3959,
              "y": 3.2485
            },
            {
              "x": 2.3959,
              "y": 3.3652
            },
            {
              "x": 1.8731,
              "y": 3.3601
            }
          ]
        },
        {
          "content": "9.00",
          "confidence": 0.978,
          "polygon": [
            {
              "x": 5.4111,
              "y": 3.2485
            },
            {
              "x": 5.6142,
              "y": 3.2485
            },
            {
              "x": 5.6142,
              "y": 3.355
            },
            {
              "x": 5.4111,
              "y": 3.355
            }
          ]
        },
        {
          "content": "152.43",
          "confidence": 0.993,
          "polygon": [
            {
              "x": 6.4822,
              "y": 3.2586
            },
            {
              "x": 6.7918,
              "y": 3.2535
            },
            {
              "x": 6.7918,
              "y": 3.355
            },
            {
              "x": 6.4873,
              "y": 3.355
            }
          ]
        },
        {
          "content": "1",
          "confidence": 0.995,
          "polygon": [
            {
              "x": 7.5786,
              "y": 3.2535
            },
            {
              "x": 7.6294,
              "y": 3.2535
            },
            {
              "x": 7.6294,
              "y": 3.355
            },
            {
              "x": 7.5786,
              "y": 3.355
            }
          ]
        },
        {
          "content": "371.87",
          "confidence": 0.983,
          "polygon": [
            {
              "x": 7.6497,
              "y": 3.2535
            },
            {
              "x": 7.9695,
              "y": 3.2535
            },
            {
              "x": 7.9695,
              "y": 3.3601
            },
            {
              "x": 7.6497,
              "y": 3.355
            }
          ]
        },
        {
          "content": "3",
          "confidence": 0.945,
          "polygon": [
            {
              "x": 0.2944,
              "y": 3.5835
            },
            {
              "x": 0.3553,
              "y": 3.5835
            },
            {
              "x": 0.3503,
              "y": 3.685
            },
            {
              "x": 0.2893,
              "y": 3.685
            }
          ]
        },
        {
          "content": "Implemented",
          "confidence": 0.961,
          "polygon": [
            {
              "x": 0.67,
              "y": 3.5885
            },
            {
              "x": 1.2792,
              "y": 3.5885
            },
            {
              "x": 1.2792,
              "y": 3.7053
            },
            {
              "x": 0.67,
              "y": 3.7002
            }
          ]
        },
        {
          "content": "6thgeneration",
          "confidence": 0.762,
          "polygon": [
            {
              "x": 1.3046,
              "y": 3.5885
            },
            {
              "x": 1.9492,
              "y": 3.5835
            },
            {
              "x": 1.9492,
              "y": 3.7053
            },
            {
              "x": 1.3046,
              "y": 3.7053
            }
          ]
        },
        {
          "content": "groupware",
          "confidence": 0.962,
          "polygon": [
            {
              "x": 1.9746,
              "y": 3.5835
            },
            {
              "x": 2.4771,
              "y": 3.5784
            },
            {
              "x": 2.4771,
              "y": 3.7103
            },
            {
              "x": 1.9746,
              "y": 3.7103
            }
          ]
        },
        {
          "content": "4.00",
          "confidence": 0.993,
          "polygon": [
            {
              "x": 5.4111,
              "y": 3.5784
            },
            {
              "x": 5.6192,
              "y": 3.5784
            },
            {
              "x": 5.6142,
              "y": 3.685
            },
            {
              "x": 5.4111,
              "y": 3.6799
            }
          ]
        },
        {
          "content": "140.87",
          "confidence": 0.995,
          "polygon": [
            {
              "x": 6.4873,
              "y": 3.5885
            },
            {
              "x": 6.7918,
              "y": 3.5885
            },
            {
              "x": 6.7918,
              "y": 3.69
            },
            {
              "x": 6.4873,
              "y": 3.69
            }
          ]
        },
        {
          "content": "563.48",
          "confidence": 0.842,
          "polygon": [
            {
              "x": 7.6395,
              "y": 3.5835
            },
            {
              "x": 7.9644,
              "y": 3.5835
            },
            {
              "x": 7.9644,
              "y": 3.69
            },
            {
              "x": 7.6446,
              "y": 3.685
            }
          ]
        },
        {
          "content": "OID",
          "confidence": 0.993,
          "polygon": [
            {
              "x": 1.7614,
              "y": 4.1113
            },
            {
              "x": 3.3705,
              "y": 4.9539
            },
            {
              "x": 2.9289,
              "y": 5.7863
            },
            {
              "x": 1.3147,
              "y": 4.9285
            }
          ]
        },
        {
          "content": "Subtotal",
          "confidence": 0.978,
          "polygon": [
            {
              "x": 6.3502,
              "y": 4.091
            },
            {
              "x": 6.7614,
              "y": 4.0859
            },
            {
              "x": 6.7614,
              "y": 4.1925
            },
            {
              "x": 6.3502,
              "y": 4.1925
            }
          ]
        },
        {
          "content": "2",
          "confidence": 0.995,
          "polygon": [
            {
              "x": 7.5634,
              "y": 4.0859
            },
            {
              "x": 7.6192,
              "y": 4.0859
            },
            {
              "x": 7.6192,
              "y": 4.1925
            },
            {
              "x": 7.5634,
              "y": 4.1925
            }
          ]
        },
        {
          "content": "602.87",
          "confidence": 0.994,
          "polygon": [
            {
              "x": 7.6497,
              "y": 4.0859
            },
            {
              "x": 7.9746,
              "y": 4.0859
            },
            {
              "x": 7.9746,
              "y": 4.1925
            },
            {
              "x": 7.6497,
              "y": 4.1925
            }
          ]
        },
        {
          "content": "Tax",
          "confidence": 0.994,
          "polygon": [
            {
              "x": 6.269,
              "y": 4.3296
            },
            {
              "x": 6.4213,
              "y": 4.3296
            },
            {
              "x": 6.4263,
              "y": 4.4514
            },
            {
              "x": 6.269,
              "y": 4.4514
            }
          ]
        },
        {
          "content": "(10%)",
          "confidence": 0.961,
          "polygon": [
            {
              "x": 6.4466,
              "y": 4.3296
            },
            {
              "x": 6.7512,
              "y": 4.3296
            },
            {
              "x": 6.7512,
              "y": 4.4616
            },
            {
              "x": 6.4466,
              "y": 4.4514
            }
          ]
        },
        {
          "content": "260.29",
          "confidence": 0.755,
          "polygon": [
            {
              "x": 7.6548,
              "y": 4.3347
            },
            {
              "x": 7.9695,
              "y": 4.3347
            },
            {
              "x": 7.9644,
              "y": 4.4412
            },
            {
              "x": 7.6548,
              "y": 4.4412
            }
          ]
        },
        {
          "content": "D.",
          "confidence": 0.995,
          "polygon": [
            {
              "x": 0.7411,
              "y": 4.6138
            },
            {
              "x": 1.0406,
              "y": 4.7813
            },
            {
              "x": 0.8985,
              "y": 5.0402
            },
            {
              "x": 0.5939,
              "y": 4.8575
            }
          ]
        },
        {
          "content": "Taylor",
          "confidence": 0.995,
          "polygon": [
            {
              "x": 1.1066,
              "y": 4.8169
            },
            {
              "x": 1.8629,
              "y": 5.2381
            },
            {
              "x": 1.7208,
              "y": 5.5122
            },
            {
              "x": 0.9645,
              "y": 5.0808
            }
          ]
        },
        {
          "content": "07/01/25",
          "confidence": 0.994,
          "polygon": [
            {
              "x": 1.9797,
              "y": 5.3041
            },
            {
              "x": 3.0558,
              "y": 5.898
            },
            {
              "x": 2.9188,
              "y": 6.1213
            },
            {
              "x": 1.8426,
              "y": 5.5782
            }
          ]
        },
        {
          "content": "Discount",
          "confidence": 0.948,
          "polygon": [
            {
              "x": 6.335,
              "y": 4.5834
            },
            {
              "x": 6.7512,
              "y": 4.5834
            },
            {
              "x": 6.7512,
              "y": 4.695
            },
            {
              "x": 6.335,
              "y": 4.69
            }
          ]
        },
        {
          "content": "-260.29",
          "confidence": 0.682,
          "polygon": [
            {
              "x": 7.6091,
              "y": 4.5834
            },
            {
              "x": 7.9644,
              "y": 4.5834
            },
            {
              "x": 7.9695,
              "y": 4.69
            },
            {
              "x": 7.6091,
              "y": 4.69
            }
          ]
        },
        {
          "content": "Total",
          "confidence": 0.992,
          "polygon": [
            {
              "x": 6.3045,
              "y": 4.8778
            },
            {
              "x": 6.5279,
              "y": 4.8778
            },
            {
              "x": 6.5279,
              "y": 4.9844
            },
            {
              "x": 6.3045,
              "y": 4.9844
            }
          ]
        },
        {
          "content": "Due",
          "confidence": 0.995,
          "polygon": [
            {
              "x": 6.5482,
              "y": 4.8778
            },
            {
              "x": 6.7411,
              "y": 4.8727
            },
            {
              "x": 6.736,
              "y": 4.9844
            },
            {
              "x": 6.5482,
              "y": 4.9844
            }
          ]
        },
        {
          "content": "2",
          "confidence": 0.997,
          "polygon": [
            {
              "x": 7.5685,
              "y": 4.8828
            },
            {
              "x": 7.6243,
              "y": 4.8828
            },
            {
              "x": 7.6243,
              "y": 4.9844
            },
            {
              "x": 7.5685,
              "y": 4.9844
            }
          ]
        },
        {
          "content": "602.87",
          "confidence": 0.961,
          "polygon": [
            {
              "x": 7.6446,
              "y": 4.8778
            },
            {
              "x": 7.9644,
              "y": 4.8828
            },
            {
              "x": 7.9644,
              "y": 4.9844
            },
            {
              "x": 7.6446,
              "y": 4.9844
            }
          ]
        },
        {
          "content": "PAYMENT",
          "confidence": 0.995,
          "polygon": [
            {
              "x": 0.3249,
              "y": 5.497
            },
            {
              "x": 0.8173,
              "y": 5.4868
            },
            {
              "x": 0.8173,
              "y": 5.5985
            },
            {
              "x": 0.3249,
              "y": 5.5934
            }
          ]
        },
        {
          "content": "INFORMATION",
          "confidence": 0.974,
          "polygon": [
            {
              "x": 0.8426,
              "y": 5.4868
            },
            {
              "x": 1.5482,
              "y": 5.4818
            },
            {
              "x": 1.5482,
              "y": 5.6036
            },
            {
              "x": 0.8376,
              "y": 5.5985
            }
          ]
        },
        {
          "content": "Bank:",
          "confidence": 0.995,
          "polygon": [
            {
              "x": 0.3249,
              "y": 5.6899
            },
            {
              "x": 0.6142,
              "y": 5.6899
            },
            {
              "x": 0.6142,
              "y": 5.8015
            },
            {
              "x": 0.3299,
              "y": 5.7965
            }
          ]
        },
        {
          "content": "Wiley-Prince",
          "confidence": 0.978,
          "polygon": [
            {
              "x": 0.6345,
              "y": 5.6899
            },
            {
              "x": 1.2284,
              "y": 5.6848
            },
            {
              "x": 1.2284,
              "y": 5.8015
            },
            {
              "x": 0.6396,
              "y": 5.8015
            }
          ]
        },
        {
          "content": "Credit",
          "confidence": 0.976,
          "polygon": [
            {
              "x": 1.2589,
              "y": 5.6848
            },
            {
              "x": 1.5533,
              "y": 5.6848
            },
            {
              "x": 1.5482,
              "y": 5.8015
            },
            {
              "x": 1.2589,
              "y": 5.8015
            }
          ]
        },
        {
          "content": "Union",
          "confidence": 0.951,
          "polygon": [
            {
              "x": 1.5736,
              "y": 5.6848
            },
            {
              "x": 1.8426,
              "y": 5.6797
            },
            {
              "x": 1.8375,
              "y": 5.8015
            },
            {
              "x": 1.5736,
              "y": 5.8015
            }
          ]
        },
        {
          "content": "Account:",
          "confidence": 0.987,
          "polygon": [
            {
              "x": 0.3249,
              "y": 5.8371
            },
            {
              "x": 0.7817,
              "y": 5.832
            },
            {
              "x": 0.7817,
              "y": 5.9437
            },
            {
              "x": 0.3299,
              "y": 5.9437
            }
          ]
        },
        {
          "content": "RLQB28889921597010",
          "confidence": 0.851,
          "polygon": [
            {
              "x": 0.8071,
              "y": 5.832
            },
            {
              "x": 1.9137,
              "y": 5.8168
            },
            {
              "x": 1.9086,
              "y": 5.9437
            },
            {
              "x": 0.8071,
              "y": 5.9437
            }
          ]
        },
        {
          "content": "Method:",
          "confidence": 0.991,
          "polygon": [
            {
              "x": 0.3198,
              "y": 5.9843
            },
            {
              "x": 0.7411,
              "y": 5.9792
            },
            {
              "x": 0.7411,
              "y": 6.0858
            },
            {
              "x": 0.3249,
              "y": 6.0858
            }
          ]
        },
        {
          "content": "Check",
          "confidence": 0.994,
          "polygon": [
            {
              "x": 0.7614,
              "y": 5.9792
            },
            {
              "x": 1.0609,
              "y": 5.9741
            },
            {
              "x": 1.0609,
              "y": 6.0858
            },
            {
              "x": 0.7665,
              "y": 6.0858
            }
          ]
        },
        {
          "content": "Thank",
          "confidence": 0.992,
          "polygon": [
            {
              "x": 3.538,
              "y": 6.5426
            },
            {
              "x": 3.7918,
              "y": 6.5477
            },
            {
              "x": 3.7918,
              "y": 6.6746
            },
            {
              "x": 3.538,
              "y": 6.6695
            }
          ]
        },
        {
          "content": "you",
          "confidence": 0.997,
          "polygon": [
            {
              "x": 3.8172,
              "y": 6.5477
            },
            {
              "x": 3.9695,
              "y": 6.5477
            },
            {
              "x": 3.9695,
              "y": 6.6746
            },
            {
              "x": 3.8172,
              "y": 6.6746
            }
          ]
        },
        {
          "content": "for",
          "confidence": 0.995,
          "polygon": [
            {
              "x": 3.9949,
              "y": 6.5477
            },
            {
              "x": 4.1066,
              "y": 6.5477
            },
            {
              "x": 4.1066,
              "y": 6.6746
            },
            {
              "x": 3.9949,
              "y": 6.6746
            }
          ]
        },
        {
          "content": "your",
          "confidence": 0.984,
          "polygon": [
            {
              "x": 4.1319,
              "y": 6.5477
            },
            {
              "x": 4.3147,
              "y": 6.5477
            },
            {
              "x": 4.3147,
              "y": 6.6746
            },
            {
              "x": 4.1319,
              "y": 6.6746
            }
          ]
        },
        {
          "content": "business",
          "confidence": 0.99,
          "polygon": [
            {
              "x": 4.3401,
              "y": 6.5477
            },
            {
              "x": 4.7258,
              "y": 6.5477
            },
            {
              "x": 4.7258,
              "y": 6.6746
            },
            {
              "x": 4.3401,
              "y": 6.6746
            }
          ]
        }
      ],
      "lines": [
        {
          "content": "Andersen-Ward",
          "polygon": [
            {
              "x": 0.1777,
              "y": 0.2233
            },
            {
              "x": 1.9188,
              "y": 0.2183
            },
            {
              "x": 1.9188,
              "y": 0.4416
            },
            {
              "x": 0.1777,
              "y": 0.4467
            }
          ]
        },
        {
          "content": "INVOICE",
          "polygon": [
            {
              "x": 6.8578,
              "y": 0.2335
            },
            {
              "x": 8.0558,
              "y": 0.2284
            },
            {
              "x": 8.0558,
              "y": 0.4822
            },
            {
              "x": 6.8578,
              "y": 0.4873
            }
          ]
        },
        {
          "content": "61434 Humphrey Lodge | Tracyport, NV 74313",
          "polygon": [
            {
              "x": 0.1878,
              "y": 0.5126
            },
            {
              "x": 2.3655,
              "y": 0.5126
            },
            {
              "x": 2.3655,
              "y": 0.6548
            },
            {
              "x": 0.1878,
              "y": 0.6548
            }
          ]
        },
        {
          "content": "No: 2508674769",
          "polygon": [
            {
              "x": 7.1878,
              "y": 0.5888
            },
            {
              "x": 8.0608,
              "y": 0.5888
            },
            {
              "x": 8.0608,
              "y": 0.7106
            },
            {
              "x": 7.1878,
              "y": 0.7106
            }
          ]
        },
        {
          "content": "Date: 12/04/2025",
          "polygon": [
            {
              "x": 7.1522,
              "y": 0.7664
            },
            {
              "x": 8.0558,
              "y": 0.7664
            },
            {
              "x": 8.0558,
              "y": 0.8882
            },
            {
              "x": 7.1522,
              "y": 0.8882
            }
          ]
        },
        {
          "content": "Due: 03/09/2026",
          "polygon": [
            {
              "x": 7.1827,
              "y": 0.9441
            },
            {
              "x": 8.0608,
              "y": 0.9441
            },
            {
              "x": 8.0608,
              "y": 1.0659
            },
            {
              "x": 7.1827,
              "y": 1.071
            }
          ]
        },
        {
          "content": "FROM",
          "polygon": [
            {
              "x": 0.1929,
              "y": 1.5582
            },
            {
              "x": 0.5533,
              "y": 1.5582
            },
            {
              "x": 0.5533,
              "y": 1.6851
            },
            {
              "x": 0.1929,
              "y": 1.6801
            }
          ]
        },
        {
          "content": "BILL TO",
          "polygon": [
            {
              "x": 4.5127,
              "y": 1.5532
            },
            {
              "x": 4.9797,
              "y": 1.5532
            },
            {
              "x": 4.9746,
              "y": 1.6851
            },
            {
              "x": 4.5127,
              "y": 1.6801
            }
          ]
        },
        {
          "content": "Andersen-Ward",
          "polygon": [
            {
              "x": 0.1878,
              "y": 1.7663
            },
            {
              "x": 1.137,
              "y": 1.7613
            },
            {
              "x": 1.137,
              "y": 1.9034
            },
            {
              "x": 0.1878,
              "y": 1.9085
            }
          ]
        },
        {
          "content": "Briggs LLC",
          "polygon": [
            {
              "x": 4.5177,
              "y": 1.7613
            },
            {
              "x": 5.203,
              "y": 1.7613
            },
            {
              "x": 5.203,
              "y": 1.9135
            },
            {
              "x": 4.5177,
              "y": 1.9135
            }
          ]
        },
        {
          "content": "61434 Humphrey Lodge",
          "polygon": [
            {
              "x": 0.1878,
              "y": 1.9389
            },
            {
              "x": 1.3401,
              "y": 1.9389
            },
            {
              "x": 1.335,
              "y": 2.0709
            },
            {
              "x": 0.1878,
              "y": 2.0607
            }
          ]
        },
        {
          "content": "0677 James Gardens Suite 403",
          "polygon": [
            {
              "x": 4.5177,
              "y": 1.9338
            },
            {
              "x": 5.9949,
              "y": 1.9338
            },
            {
              "x": 5.9949,
              "y": 2.0607
            },
            {
              "x": 4.5177,
              "y": 2.0607
            }
          ]
        },
        {
          "content": "Tracyport, NV 74313",
          "polygon": [
            {
              "x": 0.1878,
              "y": 2.0607
            },
            {
              "x": 1.1726,
              "y": 2.0557
            },
            {
              "x": 1.1726,
              "y": 2.1724
            },
            {
              "x": 0.1878,
              "y": 2.1775
            }
          ]
        },
        {
          "content": "Lake Sharon, OK 48077",
          "polygon": [
            {
              "x": 4.5127,
              "y": 2.0557
            },
            {
              "x": 5.6446,
              "y": 2.0557
            },
            {
              "x": 5.6446,
              "y": 2.1724
            },
            {
              "x": 4.5127,
              "y": 2.1724
            }
          ]
        },
        {
          "content": "#",
          "polygon": [
            {
              "x": 0.2741,
              "y": 2.5835
            },
            {
              "x": 0.3553,
              "y": 2.5785
            },
            {
              "x": 0.3604,
              "y": 2.6698
            },
            {
              "x": 0.2741,
              "y": 2.6698
            }
          ]
        },
        {
          "content": "Description",
          "polygon": [
            {
              "x": 0.6751,
              "y": 2.5683
            },
            {
              "x": 1.2538,
              "y": 2.5683
            },
            {
              "x": 1.2538,
              "y": 2.6952
            },
            {
              "x": 0.6751,
              "y": 2.6901
            }
          ]
        },
        {
          "content": "Quantity",
          "polygon": [
            {
              "x": 5.1827,
              "y": 2.5734
            },
            {
              "x": 5.6192,
              "y": 2.5734
            },
            {
              "x": 5.6192,
              "y": 2.6901
            },
            {
              "x": 5.1827,
              "y": 2.6901
            }
          ]
        },
        {
          "content": "Unit Price",
          "polygon": [
            {
              "x": 6.2994,
              "y": 2.5683
            },
            {
              "x": 6.7969,
              "y": 2.5734
            },
            {
              "x": 6.7918,
              "y": 2.68
            },
            {
              "x": 6.2994,
              "y": 2.6749
            }
          ]
        },
        {
          "content": "Amount",
          "polygon": [
            {
              "x": 7.5634,
              "y": 2.5734
            },
            {
              "x": 7.9796,
              "y": 2.5734
            },
            {
              "x": 7.9796,
              "y": 2.6749
            },
            {
              "x": 7.5634,
              "y": 2.6749
            }
          ]
        },
        {
          "content": "1",
          "polygon": [
            {
              "x": 0.2944,
              "y": 2.9287
            },
            {
              "x": 0.3452,
              "y": 2.9236
            },
            {
              "x": 0.3503,
              "y": 3.015
            },
            {
              "x": 0.2944,
              "y": 3.015
            }
          ]
        },
        {
          "content": "Balanced next generation product",
          "polygon": [
            {
              "x": 0.67,
              "y": 2.9135
            },
            {
              "x": 2.2487,
              "y": 2.9185
            },
            {
              "x": 2.2436,
              "y": 3.0353
            },
            {
              "x": 0.67,
              "y": 3.0251
            }
          ]
        },
        {
          "content": "2.00",
          "polygon": [
            {
              "x": 5.3959,
              "y": 2.9135
            },
            {
              "x": 5.6243,
              "y": 2.9135
            },
            {
              "x": 5.6243,
              "y": 3.02
            },
            {
              "x": 5.401,
              "y": 3.02
            }
          ]
        },
        {
          "content": "333.76",
          "polygon": [
            {
              "x": 6.4669,
              "y": 2.9185
            },
            {
              "x": 6.802,
              "y": 2.9185
            },
            {
              "x": 6.802,
              "y": 3.02
            },
            {
              "x": 6.4669,
              "y": 3.02
            }
          ]
        },
        {
          "content": "687.52",
          "polygon": [
            {
              "x": 7.6395,
              "y": 2.9185
            },
            {
              "x": 7.9796,
              "y": 2.9185
            },
            {
              "x": 7.9796,
              "y": 3.015
            },
            {
              "x": 7.6395,
              "y": 3.015
            }
          ]
        },
        {
          "content": "2",
          "polygon": [
            {
              "x": 0.2792,
              "y": 3.2586
            },
            {
              "x": 0.3503,
              "y": 3.2535
            },
            {
              "x": 0.3503,
              "y": 3.3601
            },
            {
              "x": 0.2843,
              "y": 3.355
            }
          ]
        },
        {
          "content": "Programmable bifurcated benchmark",
          "polygon": [
            {
              "x": 0.6497,
              "y": 3.2535
            },
            {
              "x": 2.4111,
              "y": 3.2485
            },
            {
              "x": 2.4111,
              "y": 3.3601
            },
            {
              "x": 0.6497,
              "y": 3.3703
            }
          ]
        },
        {
          "content": "9.00",
          "polygon": [
            {
              "x": 5.401,
              "y": 3.2485
            },
            {
              "x": 5.6243,
              "y": 3.2485
            },
            {
              "x": 5.6243,
              "y": 3.355
            },
            {
              "x": 5.406,
              "y": 3.355
            }
          ]
        },
        {
          "content": "152.43",
          "polygon": [
            {
              "x": 6.4669,
              "y": 3.2485
            },
            {
              "x": 6.802,
              "y": 3.2485
            },
            {
              "x": 6.802,
              "y": 3.35
            },
            {
              "x": 6.4669,
              "y": 3.355
            }
          ]
        },
        {
          "content": "1 371.87",
          "polygon": [
            {
              "x": 7.5634,
              "y": 3.2535
            },
            {
              "x": 7.9695,
              "y": 3.2535
            },
            {
              "x": 7.9695,
              "y": 3.355
            },
            {
              "x": 7.5634,
              "y": 3.35
            }
          ]
        },
        {
          "content": "3",
          "polygon": [
            {
              "x": 0.2741,
              "y": 3.5835
            },
            {
              "x": 0.3553,
              "y": 3.5835
            },
            {
              "x": 0.3553,
              "y": 3.685
            },
            {
              "x": 0.2741,
              "y": 3.6799
            }
          ]
        },
        {
          "content": "Implemented 6thgeneration groupware",
          "polygon": [
            {
              "x": 0.6548,
              "y": 3.5733
            },
            {
              "x": 2.4822,
              "y": 3.5733
            },
            {
              "x": 2.4822,
              "y": 3.7053
            },
            {
              "x": 0.6548,
              "y": 3.7053
            }
          ]
        },
        {
          "content": "4.00",
          "polygon": [
            {
              "x": 5.406,
              "y": 3.5784
            },
            {
              "x": 5.6243,
              "y": 3.5835
            },
            {
              "x": 5.6243,
              "y": 3.685
            },
            {
              "x": 5.406,
              "y": 3.685
            }
          ]
        },
        {
          "content": "140.87",
          "polygon": [
            {
              "x": 6.472,
              "y": 3.5835
            },
            {
              "x": 6.7918,
              "y": 3.5835
            },
            {
              "x": 6.7918,
              "y": 3.685
            },
            {
              "x": 6.472,
              "y": 3.685
            }
          ]
        },
        {
          "content": "563.48",
          "polygon": [
            {
              "x": 7.6345,
              "y": 3.5784
            },
            {
              "x": 7.9746,
              "y": 3.5835
            },
            {
              "x": 7.9746,
              "y": 3.69
            },
            {
              "x": 7.6345,
              "y": 3.685
            }
          ]
        },
        {
          "content": "OID",
          "polygon": [
            {
              "x": 1.7868,
              "y": 4.1113
            },
            {
              "x": 3.6446,
              "y": 5.1265
            },
            {
              "x": 3.3604,
              "y": 5.9843
            },
            {
              "x": 1.2792,
              "y": 4.9082
            }
          ]
        },
        {
          "content": "Subtotal",
          "polygon": [
            {
              "x": 6.34,
              "y": 4.0859
            },
            {
              "x": 6.7563,
              "y": 4.0809
            },
            {
              "x": 6.7563,
              "y": 4.1875
            },
            {
              "x": 6.34,
              "y": 4.1925
            }
          ]
        },
        {
          "content": "2 602.87",
          "polygon": [
            {
              "x": 7.5482,
              "y": 4.0809
            },
            {
              "x": 7.9746,
              "y": 4.0809
            },
            {
              "x": 7.9746,
              "y": 4.1875
            },
            {
              "x": 7.5482,
              "y": 4.1925
            }
          ]
        },
        {
          "content": "Tax (10%)",
          "polygon": [
            {
              "x": 6.2588,
              "y": 4.3296
            },
            {
              "x": 6.7512,
              "y": 4.3296
            },
            {
              "x": 6.7512,
              "y": 4.4565
            },
            {
              "x": 6.2588,
              "y": 4.4514
            }
          ]
        },
        {
          "content": "260.29",
          "polygon": [
            {
              "x": 7.6294,
              "y": 4.3296
            },
            {
              "x": 7.9796,
              "y": 4.3347
            },
            {
              "x": 7.9796,
              "y": 4.4362
            },
            {
              "x": 7.6294,
              "y": 4.4362
            }
          ]
        },
        {
          "content": "D. Taylor 07/01/25",
          "polygon": [
            {
              "x": 0.7157,
              "y": 4.6037
            },
            {
              "x": 3.0761,
              "y": 5.898
            },
            {
              "x": 2.9289,
              "y": 6.1315
            },
            {
              "x": 0.5787,
              "y": 4.8727
            }
          ]
        },
        {
          "content": "Discount",
          "polygon": [
            {
              "x": 6.3197,
              "y": 4.5783
            },
            {
              "x": 6.7512,
              "y": 4.5783
            },
            {
              "x": 6.7512,
              "y": 4.69
            },
            {
              "x": 6.3197,
              "y": 4.6849
            }
          ]
        },
        {
          "content": "-260.29",
          "polygon": [
            {
              "x": 7.604,
              "y": 4.5783
            },
            {
              "x": 7.9847,
              "y": 4.5834
            },
            {
              "x": 7.9796,
              "y": 4.69
            },
            {
              "x": 7.604,
              "y": 4.6849
            }
          ]
        },
        {
          "content": "Total Due",
          "polygon": [
            {
              "x": 6.2893,
              "y": 4.8727
            },
            {
              "x": 6.7461,
              "y": 4.8727
            },
            {
              "x": 6.7461,
              "y": 4.9793
            },
            {
              "x": 6.2893,
              "y": 4.9844
            }
          ]
        },
        {
          "content": "2 602.87",
          "polygon": [
            {
              "x": 7.5532,
              "y": 4.8778
            },
            {
              "x": 7.9644,
              "y": 4.8778
            },
            {
              "x": 7.9644,
              "y": 4.9793
            },
            {
              "x": 7.5532,
              "y": 4.9793
            }
          ]
        },
        {
          "content": "PAYMENT INFORMATION",
          "polygon": [
            {
              "x": 0.3198,
              "y": 5.4818
            },
            {
              "x": 1.5837,
              "y": 5.4767
            },
            {
              "x": 1.5837,
              "y": 5.5985
            },
            {
              "x": 0.3198,
              "y": 5.5985
            }
          ]
        },
        {
          "content": "Bank: Wiley-Prince Credit Union",
          "polygon": [
            {
              "x": 0.3147,
              "y": 5.6797
            },
            {
              "x": 1.8477,
              "y": 5.6746
            },
            {
              "x": 1.8477,
              "y": 5.8015
            },
            {
              "x": 0.3147,
              "y": 5.8015
            }
          ]
        },
        {
          "content": "Account: RLQB28889921597010",
          "polygon": [
            {
              "x": 0.3147,
              "y": 5.8269
            },
            {
              "x": 1.9137,
              "y": 5.8168
            },
            {
              "x": 1.9137,
              "y": 5.9437
            },
            {
              "x": 0.3198,
              "y": 5.9487
            }
          ]
        },
        {
          "content": "Method: Check",
          "polygon": [
            {
              "x": 0.3147,
              "y": 5.9741
            },
            {
              "x": 1.066,
              "y": 5.9741
            },
            {
              "x": 1.066,
              "y": 6.0858
            },
            {
              "x": 0.3198,
              "y": 6.0858
            }
          ]
        },
        {
          "content": "Thank you for your business",
          "polygon": [
            {
              "x": 3.5177,
              "y": 6.5426
            },
            {
              "x": 4.7258,
              "y": 6.5426
            },
            {
              "x": 4.7258,
              "y": 6.6746
            },
            {
              "x": 3.5177,
              "y": 6.6695
            }
          ]
        }
      ]
    }
  ],
  "tables": [
    {
      "row_count": 4,
      "column_count": 5,
      "cells": [
        {
          "row_index": 0,
          "column_index": 0,
          "content": "#",
          "kind": "columnHeader"
        },
        {
          "row_index": 0,
          "column_index": 1,
          "content": "Description",
          "kind": "columnHeader"
        },
        {
          "row_index": 0,
          "column_index": 2,
          "content": "Quantity",
          "kind": "columnHeader"
        },
        {
          "row_index": 0,
          "column_index": 3,
          "content": "Unit Price",
          "kind": "columnHeader"
        },
        {
          "row_index": 0,
          "column_index": 4,
          "content": "Amount",
          "kind": "columnHeader"
        },
        {
          "row_index": 1,
          "column_index": 0,
          "content": "1",
          "kind": "content"
        },
        {
          "row_index": 1,
          "column_index": 1,
          "content": "Balanced next generation product",
          "kind": "content"
        },
        {
          "row_index": 1,
          "column_index": 2,
          "content": "2.00",
          "kind": "content"
        },
        {
          "row_index": 1,
          "column_index": 3,
          "content": "333.76",
          "kind": "content"
        },
        {
          "row_index": 1,
          "column_index": 4,
          "content": "687.52",
          "kind": "content"
        },
        {
          "row_index": 2,
          "column_index": 0,
          "content": "2",
          "kind": "content"
        },
        {
          "row_index": 2,
          "column_index": 1,
          "content": "Programmable bifurcated benchmark",
          "kind": "content"
        },
        {
          "row_index": 2,
          "column_index": 2,
          "content": "9.00",
          "kind": "content"
        },
        {
          "row_index": 2,
          "column_index": 3,
          "content": "152.43",
          "kind": "content"
        },
        {
          "row_index": 2,
          "column_index": 4,
          "content": "1 371.87",
          "kind": "content"
        },
        {
          "row_index": 3,
          "column_index": 0,
          "content": "3",
          "kind": "content"
        },
        {
          "row_index": 3,
          "column_index": 1,
          "content": "Implemented 6thgeneration groupware",
          "kind": "content"
        },
        {
          "row_index": 3,
          "column_index": 2,
          "content": "4.00",
          "kind": "content"
        },
        {
          "row_index": 3,
          "column_index": 3,
          "content": "140.87",
          "kind": "content"
        },
        {
          "row_index": 3,
          "column_index": 4,
          "content": "563.48",
          "kind": "content"
        }
      ]
    },
    {
      "row_count": 4,
      "column_count": 2,
      "cells": [
        {
          "row_index": 0,
          "column_index": 0,
          "content": "Subtotal",
          "kind": "content"
        },
        {
          "row_index": 0,
          "column_index": 1,
          "content": "2 602.87",
          "kind": "content"
        },
        {
          "row_index": 1,
          "column_index": 0,
          "content": "Tax (10%)",
          "kind": "content"
        },
        {
          "row_index": 1,
          "column_index": 1,
          "content": "260.29",
          "kind": "content"
        },
        {
          "row_index": 2,
          "column_index": 0,
          "content": "Discount",
          "kind": "content"
        },
        {
          "row_index": 2,
          "column_index": 1,
          "content": "-260.29",
          "kind": "content"
        },
        {
          "row_index": 3,
          "column_index": 0,
          "content": "Total Due",
          "kind": "content"
        },
        {
          "row_index": 3,
          "column_index": 1,
          "content": "2 602.87",
          "kind": "content"
        }
      ]
    }
  ],
  "documents": [
    {
      "doc_type": "invoice",
      "confidence": 1.0,
      "fields": {
        "BillingAddress": {
          "value": "AddressValue(house_number=0677, po_box=None, road=James Gardens, city=Sharon, state=OK, postal_code=48077, country_region=None, street_address=0677 James Gardens Suite 403, unit=Suite 403, city_district=None, state_district=None, suburb=Lake, house=None, level=None)",
          "value_type": "address",
          "content": "0677 James Gardens Suite 403\nLake Sharon, OK 48077",
          "confidence": 0.869,
          "bounding_regions": [
            {
              "page_number": 1,
              "polygon": [
                {
                  "x": 4.5127,
                  "y": 1.9389
                },
                {
                  "x": 5.9949,
                  "y": 1.9389
                },
                {
                  "x": 5.9949,
                  "y": 2.1775
                },
                {
                  "x": 4.5127,
                  "y": 2.1775
                }
              ]
            }
          ]
        },
        "BillingAddressRecipient": {
          "value": "Briggs LLC",
          "value_type": "string",
          "content": "Briggs LLC",
          "confidence": 0.939,
          "bounding_regions": [
            {
              "page_number": 1,
              "polygon": [
                {
                  "x": 4.5177,
                  "y": 1.7612
                },
                {
                  "x": 5.1878,
                  "y": 1.7613
                },
                {
                  "x": 5.1878,
                  "y": 1.9186
                },
                {
                  "x": 4.5177,
                  "y": 1.9185
                }
              ]
            }
          ]
        },
        "CustomerId": {
          "value": "RLQB28889921597010",
          "value_type": "string",
          "content": "RLQB28889921597010",
          "confidence": 0.792,
          "bounding_regions": [
            {
              "page_number": 1,
              "polygon": [
                {
                  "x": 0.8071,
                  "y": 5.832
                },
                {
                  "x": 1.9137,
                  "y": 5.8168
                },
                {
                  "x": 1.9086,
                  "y": 5.9437
                },
                {
                  "x": 0.8071,
                  "y": 5.9437
                }
              ]
            }
          ]
        },
        "CustomerName": {
          "value": "Briggs LLC",
          "value_type": "string",
          "content": "Briggs LLC",
          "confidence": 0.939,
          "bounding_regions": [
            {
              "page_number": 1,
              "polygon": [
                {
                  "x": 4.5177,
                  "y": 1.7612
                },
                {
                  "x": 5.1878,
                  "y": 1.7613
                },
                {
                  "x": 5.1878,
                  "y": 1.9186
                },
                {
                  "x": 4.5177,
                  "y": 1.9185
                }
              ]
            }
          ]
        },
        "DueDate": {
          "value": "2026-03-09",
          "value_type": "date",
          "content": "03/09/2026",
          "confidence": 0.969,
          "bounding_regions": [
            {
              "page_number": 1,
              "polygon": [
                {
                  "x": 7.4771,
                  "y": 0.9441
                },
                {
                  "x": 8.0507,
                  "y": 0.9492
                },
                {
                  "x": 8.0507,
                  "y": 1.0659
                },
                {
                  "x": 7.4822,
                  "y": 1.071
                }
              ]
            }
          ]
        },
        "InvoiceDate": {
          "value": "2025-12-04",
          "value_type": "date",
          "content": "12/04/2025",
          "confidence": 0.969,
          "bounding_regions": [
            {
              "page_number": 1,
              "polygon": [
                {
                  "x": 7.4923,
                  "y": 0.7715
                },
                {
                  "x": 8.0558,
                  "y": 0.7715
                },
                {
                  "x": 8.0507,
                  "y": 0.8933
                },
                {
                  "x": 7.4923,
                  "y": 0.8933
                }
              ]
            }
          ]
        },
        "InvoiceId": {
          "value": "2508674769",
          "value_type": "string",
          "content": "2508674769",
          "confidence": 0.969,
          "bounding_regions": [
            {
              "page_number": 1,
              "polygon": [
                {
                  "x": 7.4162,
                  "y": 0.5888
                },
                {
                  "x": 8.0608,
                  "y": 0.5939
                },
                {
                  "x": 8.0558,
                  "y": 0.7157
                },
                {
                  "x": 7.4162,
                  "y": 0.7157
                }
              ]
            }
          ]
        },
        "InvoiceTotal": {
          "value": {
            "amount": 2602.87,
            "symbol": null,
            "code": "USD"
          },
          "value_type": "currency",
          "content": "2 602.87",
          "confidence": 0.529,
          "bounding_regions": [
            {
              "page_number": 1,
              "polygon": [
                {
                  "x": 7.5685,
                  "y": 4.8772
                },
                {
                  "x": 7.9652,
                  "y": 4.8803
                },
                {
                  "x": 7.9644,
                  "y": 4.9875
                },
                {
                  "x": 7.5677,
                  "y": 4.9844
                }
              ]
            }
          ]
        },
        "Items": {
          "value": [
            {
              "value": "{'Amount': DocumentField(value_type=currency, value=CurrencyValue(amount=687.52, symbol=None, code=USD), content=687.52, bounding_regions=[BoundingRegion(page_number=1, polygon=[Point(x=7.6497, y=2.9236), Point(x=7.9746, y=2.9185), Point(x=7.9746, y=3.02), Point(x=7.6497, y=3.02)])], spans=[DocumentSpan(offset=331, length=6)], confidence=0.959), 'Description': DocumentField(value_type=string, value='Balanced next generation product', content=Balanced next generation product, bounding_regions=[BoundingRegion(page_number=1, polygon=[Point(x=0.6701, y=2.906), Point(x=2.2499, y=2.9222), Point(x=2.2487, y=3.0446), Point(x=0.6689, y=3.0284)])], spans=[DocumentSpan(offset=286, length=32)], confidence=0.948), 'Quantity': DocumentField(value_type=float, value=2.0, content=2.00, bounding_regions=[BoundingRegion(page_number=1, polygon=[Point(x=5.4162, y=2.9135), Point(x=5.6142, y=2.9135), Point(x=5.6142, y=3.02), Point(x=5.4162, y=3.02)])], spans=[DocumentSpan(offset=319, length=4)], confidence=0.948), 'UnitPrice': DocumentField(value_type=currency, value=CurrencyValue(amount=333.76, symbol=None, code=USD), content=333.76, bounding_regions=[BoundingRegion(page_number=1, polygon=[Point(x=6.472, y=2.9185), Point(x=6.7867, y=2.9185), Point(x=6.7867, y=3.0251), Point(x=6.472, y=3.02)])], spans=[DocumentSpan(offset=324, length=6)], confidence=0.948)}",
              "value_type": "dictionary",
              "content": "1\nBalanced next generation product\n2.00\n333.76\n687.52",
              "confidence": 0.919,
              "bounding_regions": [
                {
                  "page_number": 1,
                  "polygon": [
                    {
                      "x": 0.305,
                      "y": 2.8642
                    },
                    {
                      "x": 7.9753,
                      "y": 2.9185
                    },
                    {
                      "x": 7.9741,
                      "y": 3.0837
                    },
                    {
                      "x": 0.3039,
                      "y": 3.0294
                    }
                  ]
                }
              ]
            },
            {
              "value": "{'Amount': DocumentField(value_type=currency, value=CurrencyValue(amount=1371.87, symbol=None, code=USD), content=1 371.87, bounding_regions=[BoundingRegion(page_number=1, polygon=[Point(x=7.5786, y=3.2504), Point(x=7.9704, y=3.2535), Point(x=7.9695, y=3.3601), Point(x=7.5778, y=3.357)])], spans=[DocumentSpan(offset=386, length=8)], confidence=0.945), 'Description': DocumentField(value_type=string, value='Programmable bifurcated benchmark', content=Programmable bifurcated benchmark, bounding_regions=[BoundingRegion(page_number=1, polygon=[Point(x=0.6694, y=3.2549), Point(x=2.3959, y=3.2455), Point(x=2.3965, y=3.3652), Point(x=0.67, y=3.3745)])], spans=[DocumentSpan(offset=340, length=33)], confidence=0.957), 'Quantity': DocumentField(value_type=float, value=9.0, content=9.00, bounding_regions=[BoundingRegion(page_number=1, polygon=[Point(x=5.4111, y=3.2485), Point(x=5.6142, y=3.2485), Point(x=5.6142, y=3.355), Point(x=5.4111, y=3.355)])], spans=[DocumentSpan(offset=374, length=4)], confidence=0.951), 'UnitPrice': DocumentField(value_type=currency, value=CurrencyValue(amount=152.43, symbol=None, code=USD), content=152.43, bounding_regions=[BoundingRegion(page_number=1, polygon=[Point(x=6.4822, y=3.2586), Point(x=6.7918, y=3.2535), Point(x=6.7918, y=3.355), Point(x=6.4873, y=3.355)])], spans=[DocumentSpan(offset=379, length=6)], confidence=0.947)}",
              "value_type": "dictionary",
              "content": "2\nProgrammable bifurcated benchmark\n9.00\n152.43\n1 371.87",
              "confidence": 0.917,
              "bounding_regions": [
                {
                  "page_number": 1,
                  "polygon": [
                    {
                      "x": 0.2893,
                      "y": 3.2485
                    },
                    {
                      "x": 7.9695,
                      "y": 3.2485
                    },
                    {
                      "x": 7.9695,
                      "y": 3.3703
                    },
                    {
                      "x": 0.2893,
                      "y": 3.3703
                    }
                  ]
                }
              ]
            },
            {
              "value": "{'Amount': DocumentField(value_type=currency, value=CurrencyValue(amount=563.48, symbol=None, code=USD), content=563.48, bounding_regions=[BoundingRegion(page_number=1, polygon=[Point(x=7.6395, y=3.5835), Point(x=7.9644, y=3.5835), Point(x=7.9644, y=3.69), Point(x=7.6446, y=3.685)])], spans=[DocumentSpan(offset=445, length=6)], confidence=0.957), 'Description': DocumentField(value_type=string, value='Implemented 6thgeneration groupware', content=Implemented 6thgeneration groupware, bounding_regions=[BoundingRegion(page_number=1, polygon=[Point(x=0.6696, y=3.5854), Point(x=2.4771, y=3.5784), Point(x=2.4776, y=3.7103), Point(x=0.6701, y=3.7173)])], spans=[DocumentSpan(offset=397, length=35)], confidence=0.955), 'Quantity': DocumentField(value_type=float, value=4.0, content=4.00, bounding_regions=[BoundingRegion(page_number=1, polygon=[Point(x=5.4111, y=3.5784), Point(x=5.6192, y=3.5784), Point(x=5.6142, y=3.685), Point(x=5.4111, y=3.6799)])], spans=[DocumentSpan(offset=433, length=4)], confidence=0.948), 'UnitPrice': DocumentField(value_type=currency, value=CurrencyValue(amount=140.87, symbol=None, code=USD), content=140.87, bounding_regions=[BoundingRegion(page_number=1, polygon=[Point(x=6.4873, y=3.5885), Point(x=6.7918, y=3.5885), Point(x=6.7918, y=3.69), Point(x=6.4873, y=3.69)])], spans=[DocumentSpan(offset=438, length=6)], confidence=0.947)}",
              "value_type": "dictionary",
              "content": "3\nImplemented 6thgeneration groupware\n4.00\n140.87\n563.48",
              "confidence": 0.915,
              "bounding_regions": [
                {
                  "page_number": 1,
                  "polygon": [
                    {
                      "x": 0.2893,
                      "y": 3.5784
                    },
                    {
                      "x": 7.9644,
                      "y": 3.5784
                    },
                    {
                      "x": 7.9644,
                      "y": 3.7103
                    },
                    {
                      "x": 0.2893,
                      "y": 3.7103
                    }
                  ]
                }
              ]
            }
          ],
          "value_type": "list",
          "content": null,
          "confidence": null,
          "bounding_regions": []
        },
        "SubTotal": {
          "value": {
            "amount": 2602.87,
            "symbol": null,
            "code": "USD"
          },
          "value_type": "currency",
          "content": "2 602.87",
          "confidence": 0.945,
          "bounding_regions": [
            {
              "page_number": 1,
              "polygon": [
                {
                  "x": 7.5634,
                  "y": 4.0859
                },
                {
                  "x": 7.9746,
                  "y": 4.0859
                },
                {
                  "x": 7.9746,
                  "y": 4.1925
                },
                {
                  "x": 7.5634,
                  "y": 4.1925
                }
              ]
            }
          ]
        },
        "TotalTax": {
          "value": {
            "amount": 260.29,
            "symbol": null,
            "code": "USD"
          },
          "value_type": "currency",
          "content": "260.29",
          "confidence": 0.956,
          "bounding_regions": [
            {
              "page_number": 1,
              "polygon": [
                {
                  "x": 7.6548,
                  "y": 4.3347
                },
                {
                  "x": 7.9695,
                  "y": 4.3347
                },
                {
                  "x": 7.9644,
                  "y": 4.4412
                },
                {
                  "x": 7.6548,
                  "y": 4.4412
                }
              ]
            }
          ]
        },
        "VendorAddress": {
          "value": "AddressValue(house_number=None, po_box=None, road=None, city=None, state=None, postal_code=61434, country_region=None, street_address=, unit=None, city_district=None, state_district=None, suburb=None, house=Humphrey Lodge | Tracyport, NV, level=None)",
          "value_type": "address",
          "content": "61434 Humphrey Lodge | Tracyport, NV 74313",
          "confidence": 0.685,
          "bounding_regions": [
            {
              "page_number": 1,
              "polygon": [
                {
                  "x": 0.198,
                  "y": 0.5177
                },
                {
                  "x": 2.3705,
                  "y": 0.5177
                },
                {
                  "x": 2.3705,
                  "y": 0.6598
                },
                {
                  "x": 0.198,
                  "y": 0.6598
                }
              ]
            }
          ]
        },
        "VendorAddressRecipient": {
          "value": "Andersen-Ward",
          "value_type": "string",
          "content": "Andersen-Ward",
          "confidence": 0.351,
          "bounding_regions": [
            {
              "page_number": 1,
              "polygon": [
                {
                  "x": 0.203,
                  "y": 1.7714
                },
                {
                  "x": 1.1269,
                  "y": 1.7663
                },
                {
                  "x": 1.1269,
                  "y": 1.9085
                },
                {
                  "x": 0.2081,
                  "y": 1.9135
                }
              ]
            }
          ]
        },
        "VendorName": {
          "value": "Andersen-Ward",
          "value_type": "string",
          "content": "Andersen-Ward",
          "confidence": 0.843,
          "bounding_regions": [
            {
              "page_number": 1,
              "polygon": [
                {
                  "x": 0.2081,
                  "y": 0.2233
                },
                {
                  "x": 1.8731,
                  "y": 0.2183
                },
                {
                  "x": 1.8782,
                  "y": 0.4467
                },
                {
                  "x": 0.2081,
                  "y": 0.4517
                }
              ]
            }
          ]
        }
      }
    }
  ]
}